abacus/VERSION
abacus/__init__.py
abacus/types.py
abacus/version.py
abacus/auto_ab/__init__.py
abacus/auto_ab/abtest.py
abacus/auto_ab/graphics.py
abacus/auto_ab/params.py
abacus/auto_ab/variance_reduction.py
abacus/mde_researcher/__init__.py
abacus/mde_researcher/_abstract_mde_experiment_builder.py
abacus/mde_researcher/_experiment_structures.py
abacus/mde_researcher/mde_research_builder.py
abacus/mde_researcher/multiple_split_builder.py
abacus/mde_researcher/params.py
abacus/resplitter/__init__.py
abacus/resplitter/params.py
abacus/resplitter/resplit_builder.py
abacus/splitter/__init__.py
abacus/splitter/params.py
abacus/splitter/split_builder.py
kolmogorov_abacus-0.0.6.dist-info/LICENSE
kolmogorov_abacus-0.0.6.dist-info/METADATA
kolmogorov_abacus-0.0.6.dist-info/WHEEL
kolmogorov_abacus-0.0.6.dist-info/top_level.txt
kolmogorov_abacus-0.0.6.dist-info/RECORD
