Metadata-Version: 2.1
Name: kolmogorov-abacus
Version: 0.0.6
Summary: A/B experiments planning and evaluation tool
Author-email: Vadim Glukhov <educauchy@gmail.com>, Egor Shishkovets <egor.shishkovets@glowbyteconsulting.com>, Dmitry Zabavin <dmitriy.zabavin@glowbyteconsulting.com>
License: MIT License
Project-URL: Homepage, https://kolmogorov-abacus.readthedocs.io/
Project-URL: Repository, https://github.com/kolmogorov-lab/abacus/
Project-URL: Ecosystem, https://kolmogorov.ai/
Keywords: A/B,experiments,OCE,online controlled experiment,ab test,experiment design
Classifier: License :: OSI Approved :: MIT License
Classifier: Programming Language :: Python
Classifier: Programming Language :: Python :: 3
Classifier: Programming Language :: Python :: 3 :: Only
Classifier: Programming Language :: Python :: 3.8
Classifier: Topic :: Scientific/Engineering
Requires-Python: >=3.8
License-File: LICENSE
Requires-Dist: numpy <1.25,>=1.24
Requires-Dist: pandas <2.0,>=1.5.0
Requires-Dist: scikit-learn >=1.3.0
Requires-Dist: scipy <1.11,>=1.10.0
Requires-Dist: statsmodels <0.15,>=0.13.5
Requires-Dist: matplotlib <3.9,>=3.7.0
Requires-Dist: seaborn <0.14,>=0.12.0
Requires-Dist: category-encoders >=2.4.1
Requires-Dist: fastcore <1.6,>=1.4.0
Requires-Dist: pydantic <2.0,>=1.9.0
